{
  "docs": {
    "OpEn Guide": [
      "open-intro",
      "installation",
      "algorithm"
    ],
    "Python": [
      "python-interface",
      "python-advanced",
      "python-c",
      "python-tcp-ip",
      "python-examples"
    ],
    "MATLAB": [
      "matlab-interface",
      "udp-sockets",
      "matlab-examples"
    ],
    "Rust": [
      "openrust-basic",
      "openrust-alm"
    ],
    "Extras": [
      "faq",
      "contributing"
    ]
  },
  "examples": {
    "Python": [
      "example_rosenbrock_py",
      "example_navigation_py",
      "example_estimation_py"
    ]
  },
  "docs-other": {
    "First Category": [
      "doc5"
    ]
  }
}